xrcon-0.1.dist-info/RECORD
xrcon-0.1.dist-info/WHEEL
xrcon-0.1.dist-info/entry_points.txt
xrcon-0.1.dist-info/DESCRIPTION.rst
xrcon-0.1.dist-info/metadata.json
xrcon-0.1.dist-info/top_level.txt
xrcon-0.1.dist-info/METADATA
xrcon/commands.py
xrcon/client.py
xrcon/utils.py
xrcon/__init__.py
