Metadata-Version: 2.0
Name: xrcon
Version: 0.1
Summary: Quake and DarkPlaces rcon client.Suppor such games like Xonotic, Nexuiz and other
Home-page: https://github.com/bacher09/xrcon
Author: Slava Bacherikov
Author-email: slava@bacher09.org
License: LGPL
Keywords: rcon,xonotic,nexuiz,darkplaces,quake
Platform: any
Classifier: Development Status :: 3 - Alpha
Classifier: Operating System :: OS Independent
Classifier: Intended Audience :: Developers
Classifier: License :: OSI Approved :: GNU Library or Lesser General Public License (LGPL)
Classifier: Programming Language :: Python
Classifier: Programming Language :: Python :: 2
Classifier: Programming Language :: Python :: 2.6
Classifier: Programming Language :: Python :: 2.7
Classifier: Programming Language :: Python :: 3
Classifier: Programming Language :: Python :: 3.2
Classifier: Programming Language :: Python :: 3.3
Classifier: Programming Language :: Python :: 3.4
Classifier: Topic :: Software Development :: Libraries
Classifier: Topic :: Internet
Requires-Dist: six
